par_mcp_inspector_tui/__init__.py
par_mcp_inspector_tui/__main__.py
par_mcp_inspector_tui/logging_config.py
par_mcp_inspector_tui/py.typed
par_mcp_inspector_tui/client/__init__.py
par_mcp_inspector_tui/client/base.py
par_mcp_inspector_tui/client/http.py
par_mcp_inspector_tui/client/stdio.py
par_mcp_inspector_tui/client/tcp.py
par_mcp_inspector_tui/models/__init__.py
par_mcp_inspector_tui/models/base.py
par_mcp_inspector_tui/models/prompt.py
par_mcp_inspector_tui/models/resource.py
par_mcp_inspector_tui/models/root.py
par_mcp_inspector_tui/models/server.py
par_mcp_inspector_tui/models/tool.py
par_mcp_inspector_tui/services/__init__.py
par_mcp_inspector_tui/services/mcp_service.py
par_mcp_inspector_tui/services/server_manager.py
par_mcp_inspector_tui/tui/__init__.py
par_mcp_inspector_tui/tui/app.py
par_mcp_inspector_tui/tui/app.tcss
par_mcp_inspector_tui/tui/widgets/__init__.py
par_mcp_inspector_tui/tui/widgets/confirmation_dialog.py
par_mcp_inspector_tui/tui/widgets/connection_status.py
par_mcp_inspector_tui/tui/widgets/dynamic_form.py
par_mcp_inspector_tui/tui/widgets/notification_panel.py
par_mcp_inspector_tui/tui/widgets/prompts_view.py
par_mcp_inspector_tui/tui/widgets/raw_interactions_view.py
par_mcp_inspector_tui/tui/widgets/resources_view.py
par_mcp_inspector_tui/tui/widgets/response_viewer.py
par_mcp_inspector_tui/tui/widgets/roots_view.py
par_mcp_inspector_tui/tui/widgets/server_dialog.py
par_mcp_inspector_tui/tui/widgets/server_panel.py
par_mcp_inspector_tui/tui/widgets/tools_view.py
par_mcp_inspector_tui/utils/__init__.py
par_mcp_inspector_tui/utils/content_detection.py
par_mcp_inspector_tui-0.9.0.dist-info/METADATA
par_mcp_inspector_tui-0.9.0.dist-info/WHEEL
par_mcp_inspector_tui-0.9.0.dist-info/entry_points.txt
par_mcp_inspector_tui-0.9.0.dist-info/licenses/LICENSE
par_mcp_inspector_tui-0.9.0.dist-info/RECORD
