Metadata-Version: 2.4
Name: par-mcp-inspector-tui
Version: 0.9.0
Summary: PAR MCP Inspector TUI - Terminal interface for MCP servers with smart content detection, syntax highlighting, and protocol debugging
Project-URL: Homepage, https://github.com/paulrobello/par-mcp-inspector-tui
Project-URL: Documentation, https://github.com/paulrobello/par-mcp-inspector-tui/blob/main/README.md
Project-URL: Repository, https://github.com/paulrobello/par-mcp-inspector-tui
Project-URL: Issues, https://github.com/paulrobello/par-mcp-inspector-tui/issues
Project-URL: Discussions, https://github.com/paulrobello/par-mcp-inspector-tui/discussions
Project-URL: Wiki, https://github.com/paulrobello/par-mcp-inspector-tui/wiki
Author-email: Paul Robello <probello@gmail.com>
Maintainer-email: Paul Robello <probello@gmail.com>
License: MIT License
License-File: LICENSE
Keywords: mcp,terminal,tui
Classifier: Development Status :: 4 - Beta
Classifier: Environment :: Console
Classifier: Intended Audience :: Developers
Classifier: Intended Audience :: End Users/Desktop
Classifier: Intended Audience :: Other Audience
Classifier: License :: OSI Approved :: MIT License
Classifier: Operating System :: MacOS
Classifier: Operating System :: Microsoft :: Windows :: Windows 10
Classifier: Operating System :: Microsoft :: Windows :: Windows 11
Classifier: Operating System :: POSIX :: Linux
Classifier: Programming Language :: Python :: 3
Classifier: Programming Language :: Python :: 3.11
Classifier: Programming Language :: Python :: 3.12
Classifier: Programming Language :: Python :: 3.13
Classifier: Topic :: Software Development :: Libraries :: Python Modules
Classifier: Typing :: Typed
Requires-Python: >=3.11
Requires-Dist: fastmcp>=2.11.0
Requires-Dist: filetype>=1.2.0
Requires-Dist: pydantic-core>=2.33.2
Requires-Dist: pydantic>=2.11.7
Requires-Dist: pyperclip>=1.9.0
Requires-Dist: python-dotenv>=1.1.1
Requires-Dist: pyyaml>=6.0.2
Requires-Dist: rich>=14.1.0
Requires-Dist: textual[syntax]>=5.2.0
Requires-Dist: typer>=0.16.0
Requires-Dist: websockets>=15.0.1
